{"MSA": {"LSZ": {"0": [14893, "XHZ"], "1": [2809, "XHZ"], "2": [5618, "XHZ"], "3": [8427, "XHZ"], "4": [11236, "XHZ"], "5": [14045, "XHZ"], "6": [1961, "XHZ"], "7": [4770, "XHZ"], "8": [7579, "XHZ"], "9": [10388, "XHZ"], "10": [13197, "XHZ"], "11": [1113, "XHZ"], "12": [3922, "XHZ"], "13": [6731, "XHZ"], "14": [9540, "XHZ"], "15": [12349, "XHZ"], "16": [265, "XHZ"], "17": [3074, "XHZ"], "18": [5883, "XHZ"], "19": [8692, "XHZ"], "20": [11501, "XHZ"], "21": [14310, "XHZ"], "22": [2226, "XHZ"], "23": [5035, "XHZ"], "24": [7844, "XHZ"], "25": [10653, "XHZ"], "26": [13462, "XHZ"], "27": [1378, "XHZ"], "28": [4187, "XHZ"], "29": [6996, "XHZ"], "30": [9805, "XHZ"], "31": [12614, "XHZ"], "32": [530, "XHZ"], "33": [3339, "XHZ"], "34": [6148, "XHZ"], "35": [8957, "XHZ"], "36": [11766, "XHZ"], "37": [14575, "XHZ"], "38": [2491, "XHZ"], "39": [5300, "XHZ"], "40": [8109, "XHZ"], "41": [10918, "XHZ"], "42": [13727, "XHZ"], "43": [1643, "XHZ"], "44": [4452, "XHZ"], "45": [7261, "XHZ"], "46": [10070, "XHZ"], "47": [12879, "XHZ"], "48": [795, "XHZ"], "49": [3604, "XHZ"], "50": [6413, "XHZ"], "51": [9222, "XHZ"], "52": [12031, "XHZ"], "53": [14840, "XHZ"], "54": [2756, "XHZ"], "55": [5565, "XHZ"], "56": [8374, "XHZ"], "57": [11183, "XHZ"], "58": [13992, "XHZ"], "59": [1908, "XHZ"], "60": [4717, "XHZ"], "61": [7526, "XHZ"], "62": [10335, "XHZ"], "63": [13144, "XHZ"], "64": [1060, "XHZ"], "65": [3869, "XHZ"], "66": [6678, "XHZ"], "67": [9487, "XHZ"], "68": [12296, "XHZ"], "69": [212, "XHZ"], "70": [3021, "XHZ"], "71": [5830, "XHZ"], "72": [8639, "XHZ"], "73": [11448, "XHZ"], "74": [14257, "XHZ"], "75": [2173, "XHZ"], "76": [4982, "XHZ"], "77": [7791, "XHZ"], "78": [10600, "XHZ"], "79": [13409, "XHZ"], "80": [1325, "XHZ"], "81": [4134, "XHZ"], "82": [6943, "XHZ"], "83": [9752, "XHZ"], "84": [12561, "XHZ"], "85": [477, "XHZ"], "86": [3286, "XHZ"], "87": [6095, "XHZ"], "88": [8904, "XHZ"], "89": [11713, "XHZ"], "90": [14522, "XHZ"], "91": [2438, "XHZ"], "92": [5247, "XHZ"], "93": [8056, "XHZ"], "94": [10865, "XHZ"], "95": [13674, "XHZ"], "96": [1590, "XHZ"], "97": [4399, "XHZ"], "98": [7208, "XHZ"], "99": [10017, "XHZ"], "100": [12826, "XHZ"], "101": [742, "XHZ"], "102": [3551, "XHZ"], "103": [6360, "XHZ"], "104": [9169, "XHZ"], "105": [11978, "XHZ"], "106": [14787, "XHZ"], "107": [2703, "XHZ"], "108": [5512, "XHZ"], "109": [8321, "XHZ"], "110": [11130, "XHZ"], "111": [13939, "XHZ"], "112": [1855, "XHZ"], "113": [4664, "XHZ"], "114": [7473, "XHZ"], "115": [10282, "XHZ"], "116": [13091, "XHZ"], "117": [1007, "XHZ"], "118": [3816, "XHZ"], "119": [6625, "XHZ"], "120": [9434, "XHZ"], "121": [12243, "XHZ"], "122": [159, "XHZ"], "123": [2968, "XHZ"], "124": [5777, "XHZ"], "125": [8586, "XHZ"], "126": [11395, "XHZ"], "127": [14204, "XHZ"], "128": [2120, "XHZ"], "129": [4929, "XHZ"], "130": [7738, "XHZ"], "131": [10547, "XHZ"], "132": [13356, "XHZ"], "133": [1272, "XHZ"], "134": [4081, "XHZ"], "135": [6890, "XHZ"], "136": [9699, "XHZ"], "137": [12508, "XHZ"], "138": [424, "XHZ"], "139": [3233, "XHZ"], "140": [6042, "XHZ"], "141": [8851, "XHZ"], "142": [11660, "XHZ"], "143": [14469, "XHZ"], "144": [2385, "XHZ"], "145": [5194, "XHZ"], "146": [8003, "XHZ"], "147": [10812, "XHZ"], "148": [13621, "XHZ"], "149": [1537, "XHZ"], "150": [4346, "XHZ"], "151": [7155, "XHZ"], "152": [9964, "XHZ"], "153": [12773, "XHZ"], "154": [689, "XHZ"], "155": [3498, "XHZ"], "156": [6307, "XHZ"], "157": [9116, "XHZ"], "158": [11925, "XHZ"], "159": [14734, "XHZ"], "160": [2650, "XHZ"], "161": [5459, "XHZ"], "162": [8268, "XHZ"], "163": [11077, "XHZ"], "164": [13886, "XHZ"], "165": [1802, "XHZ"], "166": [4611, "XHZ"], "167": [7420, "XHZ"], "168": [10229, "XHZ"], "169": [13038, "XHZ"], "170": [954, "XHZ"], "171": [3763, "XHZ"], "172": [6572, "XHZ"], "173": [9381, "XHZ"], "174": [12190, "XHZ"], "175": [106, "XHZ"], "176": [2915, "XHZ"], "177": [5724, "XHZ"], "178": [8533, "XHZ"], "179": [11342, "XHZ"], "180": [14151, "XHZ"], "181": [2067, "XHZ"], "182": [4876, "XHZ"], "183": [7685, "XHZ"], "184": [10494, "XHZ"], "185": [13303, "XHZ"], "186": [1219, "XHZ"], "187": [4028, "XHZ"], "188": [6837, "XHZ"], "189": [9646, "XHZ"], "190": [12455, "XHZ"], "191": [371, "XHZ"], "192": [3180, "XHZ"], "193": [5989, "XHZ"], "194": [8798, "XHZ"], "195": [11607, "XHZ"], "196": [14416, "XHZ"], "197": [2332, "XHZ"], "198": [5141, "XHZ"], "199": [7950, "XHZ"], "200": [10759, "XHZ"], "201": [13568, "XHZ"], "202": [1484, "XHZ"], "203": [4293, "XHZ"], "204": [7102, "XHZ"], "205": [9911, "XHZ"], "206": [12720, "XHZ"], "207": [636, "XHZ"], "208": [3445, "XHZ"], "209": [6254, "XHZ"], "210": [9063, "XHZ"], "211": [11872, "XHZ"], "212": [14681, "XHZ"], "213": [2597, "XHZ"], "214": [5406, "XHZ"], "215": [8215, "XHZ"], "216": [11024, "XHZ"], "217": [13833, "XHZ"], "218": [1749, "XHZ"], "219": [4558, "XHZ"], "220": [7367, "XHZ"], "221": [10176, "XHZ"], "222": [12985, "XHZ"], "223": [901, "XHZ"], "224": [3710, "XHZ"], "225": [6519, "XHZ"], "226": [9328, "XHZ"], "227": [12137, "XHZ"], "228": [53, "XHZ"], "229": [2862, "XHZ"], "230": [5671, "XHZ"], "231": [8480, "XHZ"], "232": [11289, "XHZ"], "233": [14098, "XHZ"], "234": [2014, "XHZ"], "235": [4823, "XHZ"], "236": [7632, "XHZ"], "237": [10441, "XHZ"], "238": [13250, "XHZ"], "239": [1166, "XHZ"], "240": [3975, "XHZ"], "241": [6784, "XHZ"], "242": [9593, "XHZ"], "243": [12402, "XHZ"], "244": [318, "XHZ"], "245": [3127, "XHZ"], "246": [5936, "XHZ"], "247": [8745, "XHZ"], "248": [11554, "XHZ"], "249": [14363, "XHZ"], "250": [2279, "XHZ"], "251": [5088, "XHZ"], "252": [7897, "XHZ"], "253": [10706, "XHZ"], "254": [13515, "XHZ"], "255": [1431, "XHZ"], "256": [4240, "XHZ"], "257": [7049, "XHZ"], "258": [9858, "XHZ"], "259": [12667, "XHZ"], "260": [583, "XHZ"], "261": [3392, "XHZ"], "262": [6201, "XHZ"], "263": [9010, "XHZ"], "264": [11819, "XHZ"], "265": [14628, "XHZ"], "266": [2544, "XHZ"], "267": [5353, "XHZ"], "268": [8162, "XHZ"], "269": [10971, "XHZ"], "270": [13780, "XHZ"], "271": [1696, "XHZ"], "272": [4505, "XHZ"], "273": [7314, "XHZ"], "274": [10123, "XHZ"], "275": [12932, "XHZ"], "276": [848, "XHZ"], "277": [3657, "XHZ"], "278": [6466, "XHZ"], "279": [9275, "XHZ"], "280": [12084, "XHZ"]}, "ZZZ": {"0": [14893, "XHZ"], "1": [2809, "XHZ"], "2": [5618, "XHZ"], "3": [8427, "XHZ"], "4": [11236, "XHZ"], "5": [14045, "XHZ"], "6": [1961, "XHZ"], "7": [4770, "XHZ"], "8": [7579, "XHZ"], "9": [10388, "XHZ"], "10": [13197, "XHZ"], "11": [1113, "XHZ"], "12": [3922, "XHZ"], "13": [6731, "XHZ"], "14": [9540, "XHZ"], "15": [12349, "XHZ"], "16": [265, "XHZ"], "17": [3074, "XHZ"], "18": [5883, "XHZ"], "19": [8692, "XHZ"], "20": [11501, "XHZ"], "21": [14310, "XHZ"], "22": [2226, "XHZ"], "23": [5035, "XHZ"], "24": [7844, "XHZ"], "25": [10653, "XHZ"], "26": [13462, "XHZ"], "27": [1378, "XHZ"], "28": [4187, "XHZ"], "29": [6996, "XHZ"], "30": [9805, "XHZ"], "31": [12614, "XHZ"], "32": [530, "XHZ"], "33": [3339, "XHZ"], "34": [6148, "XHZ"], "35": [8957, "XHZ"], "36": [11766, "XHZ"], "37": [14575, "XHZ"], "38": [2491, "XHZ"], "39": [5300, "XHZ"], "40": [8109, "XHZ"], "41": [10918, "XHZ"], "42": [13727, "XHZ"], "43": [1643, "XHZ"], "44": [4452, "XHZ"], "45": [7261, "XHZ"], "46": [10070, "XHZ"], "47": [12879, "XHZ"], "48": [795, "XHZ"], "49": [3604, "XHZ"], "50": [6413, "XHZ"], "51": [9222, "XHZ"], "52": [12031, "XHZ"], "53": [14840, "XHZ"], "54": [2756, "XHZ"], "55": [5565, "XHZ"], "56": [8374, "XHZ"], "57": [11183, "XHZ"], "58": [13992, "XHZ"], "59": [1908, "XHZ"], "60": [4717, "XHZ"], "61": [7526, "XHZ"], "62": [10335, "XHZ"], "63": [13144, "XHZ"], "64": [1060, "XHZ"], "65": [3869, "XHZ"], "66": [6678, "XHZ"], "67": [9487, "XHZ"], "68": [12296, "XHZ"], "69": [212, "XHZ"], "70": [3021, "XHZ"], "71": [5830, "XHZ"], "72": [8639, "XHZ"], "73": [11448, "XHZ"], "74": [14257, "XHZ"], "75": [2173, "XHZ"], "76": [4982, "XHZ"], "77": [7791, "XHZ"], "78": [10600, "XHZ"], "79": [13409, "XHZ"], "80": [1325, "XHZ"], "81": [4134, "XHZ"], "82": [6943, "XHZ"], "83": [9752, "XHZ"], "84": [12561, "XHZ"], "85": [477, "XHZ"], "86": [3286, "XHZ"], "87": [6095, "XHZ"], "88": [8904, "XHZ"], "89": [11713, "XHZ"], "90": [14522, "XHZ"], "91": [2438, "XHZ"], "92": [5247, "XHZ"], "93": [8056, "XHZ"], "94": [10865, "XHZ"], "95": [13674, "XHZ"], "96": [1590, "XHZ"], "97": [4399, "XHZ"], "98": [7208, "XHZ"], "99": [10017, "XHZ"], "100": [12826, "XHZ"], "101": [742, "XHZ"], "102": [3551, "XHZ"], "103": [6360, "XHZ"], "104": [9169, "XHZ"], "105": [11978, "XHZ"], "106": [14787, "XHZ"], "107": [2703, "XHZ"], "108": [5512, "XHZ"], "109": [8321, "XHZ"], "110": [11130, "XHZ"], "111": [13939, "XHZ"], "112": [1855, "XHZ"], "113": [4664, "XHZ"], "114": [7473, "XHZ"], "115": [10282, "XHZ"], "116": [13091, "XHZ"], "117": [1007, "XHZ"], "118": [3816, "XHZ"], "119": [6625, "XHZ"], "120": [9434, "XHZ"], "121": [12243, "XHZ"], "122": [159, "XHZ"], "123": [2968, "XHZ"], "124": [5777, "XHZ"], "125": [8586, "XHZ"], "126": [11395, "XHZ"], "127": [14204, "XHZ"], "128": [2120, "XHZ"], "129": [4929, "XHZ"], "130": [7738, "XHZ"], "131": [10547, "XHZ"], "132": [13356, "XHZ"], "133": [1272, "XHZ"], "134": [4081, "XHZ"], "135": [6890, "XHZ"], "136": [9699, "XHZ"], "137": [12508, "XHZ"], "138": [424, "XHZ"], "139": [3233, "XHZ"], "140": [6042, "XHZ"], "141": [8851, "XHZ"], "142": [11660, "XHZ"], "143": [14469, "XHZ"], "144": [2385, "XHZ"], "145": [5194, "XHZ"], "146": [8003, "XHZ"], "147": [10812, "XHZ"], "148": [13621, "XHZ"], "149": [1537, "XHZ"], "150": [4346, "XHZ"], "151": [7155, "XHZ"], "152": [9964, "XHZ"], "153": [12773, "XHZ"], "154": [689, "XHZ"], "155": [3498, "XHZ"], "156": [6307, "XHZ"], "157": [9116, "XHZ"], "158": [11925, "XHZ"], "159": [14734, "XHZ"], "160": [2650, "XHZ"], "161": [5459, "XHZ"], "162": [8268, "XHZ"], "163": [11077, "XHZ"], "164": [13886, "XHZ"], "165": [1802, "XHZ"], "166": [4611, "XHZ"], "167": [7420, "XHZ"], "168": [10229, "XHZ"], "169": [13038, "XHZ"], "170": [954, "XHZ"], "171": [3763, "XHZ"], "172": [6572, "XHZ"], "173": [9381, "XHZ"], "174": [12190, "XHZ"], "175": [106, "XHZ"], "176": [2915, "XHZ"], "177": [5724, "XHZ"], "178": [8533, "XHZ"], "179": [11342, "XHZ"], "180": [14151, "XHZ"], "181": [2067, "XHZ"], "182": [4876, "XHZ"], "183": [7685, "XHZ"], "184": [10494, "XHZ"], "185": [13303, "XHZ"], "186": [1219, "XHZ"], "187": [4028, "XHZ"], "188": [6837, "XHZ"], "189": [9646, "XHZ"], "190": [12455, "XHZ"], "191": [371, "XHZ"], "192": [3180, "XHZ"], "193": [5989, "XHZ"], "194": [8798, "XHZ"], "195": [11607, "XHZ"], "196": [14416, "XHZ"], "197": [2332, "XHZ"], "198": [5141, "XHZ"], "199": [7950, "XHZ"], "200": [10759, "XHZ"], "201": [13568, "XHZ"], "202": [1484, "XHZ"], "203": [4293, "XHZ"], "204": [7102, "XHZ"], "205": [9911, "XHZ"], "206": [12720, "XHZ"], "207": [636, "XHZ"], "208": [3445, "XHZ"], "209": [6254, "XHZ"], "210": [9063, "XHZ"], "211": [11872, "XHZ"], "212": [14681, "XHZ"], "213": [2597, "XHZ"], "214": [5406, "XHZ"], "215": [8215, "XHZ"], "216": [11024, "XHZ"], "217": [13833, "XHZ"], "218": [1749, "XHZ"], "219": [4558, "XHZ"], "220": [7367, "XHZ"], "221": [10176, "XHZ"], "222": [12985, "XHZ"], "223": [901, "XHZ"], "224": [3710, "XHZ"], "225": [6519, "XHZ"], "226": [9328, "XHZ"], "227": [12137, "XHZ"], "228": [53, "XHZ"], "229": [2862, "XHZ"], "230": [5671, "XHZ"], "231": [8480, "XHZ"], "232": [11289, "XHZ"], "233": [14098, "XHZ"], "234": [2014, "XHZ"], "235": [4823, "XHZ"], "236": [7632, "XHZ"], "237": [10441, "XHZ"], "238": [13250, "XHZ"], "239": [1166, "XHZ"], "240": [3975, "XHZ"], "241": [6784, "XHZ"], "242": [9593, "XHZ"], "243": [12402, "XHZ"], "244": [318, "XHZ"], "245": [3127, "XHZ"], "246": [5936, "XHZ"], "247": [8745, "XHZ"], "248": [11554, "XHZ"], "249": [14363, "XHZ"], "250": [2279, "XHZ"], "251": [5088, "XHZ"], "252": [7897, "XHZ"], "253": [10706, "XHZ"], "254": [13515, "XHZ"], "255": [1431, "XHZ"], "256": [4240, "XHZ"], "257": [7049, "XHZ"], "258": [9858, "XHZ"], "259": [12667, "XHZ"], "260": [583, "XHZ"], "261": [3392, "XHZ"], "262": [6201, "XHZ"], "263": [9010, "XHZ"], "264": [11819, "XHZ"], "265": [14628, "XHZ"], "266": [2544, "XHZ"], "267": [5353, "XHZ"], "268": [8162, "XHZ"], "269": [10971, "XHZ"], "270": [13780, "XHZ"], "271": [1696, "XHZ"], "272": [4505, "XHZ"], "273": [7314, "XHZ"], "274": [10123, "XHZ"], "275": [12932, "XHZ"], "276": [848, "XHZ"], "277": [3657, "XHZ"], "278": [6466, "XHZ"], "279": [9275, "XHZ"], "280": [12084, "XHZ"]}, "XHZ": {"0": [14893, "XHZ"], "1": [2809, "XHZ"], "2": [5618, "XHZ"], "3": [8427, "XHZ"], "4": [11236, "XHZ"], "5": [14045, "XHZ"], "6": [1961, "XHZ"], "7": [4770, "XHZ"], "8": [7579, "XHZ"], "9": [10388, "XHZ"], "10": [13197, "XHZ"], "11": [1113, "XHZ"], "12": [3922, "XHZ"], "13": [6731, "XHZ"], "14": [9540, "XHZ"], "15": [12349, "XHZ"], "16": [265, "XHZ"], "17": [3074, "XHZ"], "18": [5883, "XHZ"], "19": [8692, "XHZ"], "20": [11501, "XHZ"], "21": [14310, "XHZ"], "22": [2226, "XHZ"], "23": [5035, "XHZ"], "24": [7844, "XHZ"], "25": [10653, "XHZ"], "26": [13462, "XHZ"], "27": [1378, "XHZ"], "28": [4187, "XHZ"], "29": [6996, "XHZ"], "30": [9805, "XHZ"], "31": [12614, "XHZ"], "32": [530, "XHZ"], "33": [3339, "XHZ"], "34": [6148, "XHZ"], "35": [8957, "XHZ"], "36": [11766, "XHZ"], "37": [14575, "XHZ"], "38": [2491, "XHZ"], "39": [5300, "XHZ"], "40": [8109, "XHZ"], "41": [10918, "XHZ"], "42": [13727, "XHZ"], "43": [1643, "XHZ"], "44": [4452, "XHZ"], "45": [7261, "XHZ"], "46": [10070, "XHZ"], "47": [12879, "XHZ"], "48": [795, "XHZ"], "49": [3604, "XHZ"], "50": [6413, "XHZ"], "51": [9222, "XHZ"], "52": [12031, "XHZ"], "53": [14840, "XHZ"], "54": [2756, "XHZ"], "55": [5565, "XHZ"], "56": [8374, "XHZ"], "57": [11183, "XHZ"], "58": [13992, "XHZ"], "59": [1908, "XHZ"], "60": [4717, "XHZ"], "61": [7526, "XHZ"], "62": [10335, "XHZ"], "63": [13144, "XHZ"], "64": [1060, "XHZ"], "65": [3869, "XHZ"], "66": [6678, "XHZ"], "67": [9487, "XHZ"], "68": [12296, "XHZ"], "69": [212, "XHZ"], "70": [3021, "XHZ"], "71": [5830, "XHZ"], "72": [8639, "XHZ"], "73": [11448, "XHZ"], "74": [14257, "XHZ"], "75": [2173, "XHZ"], "76": [4982, "XHZ"], "77": [7791, "XHZ"], "78": [10600, "XHZ"], "79": [13409, "XHZ"], "80": [1325, "XHZ"], "81": [4134, "XHZ"], "82": [6943, "XHZ"], "83": [9752, "XHZ"], "84": [12561, "XHZ"], "85": [477, "XHZ"], "86": [3286, "XHZ"], "87": [6095, "XHZ"], "88": [8904, "XHZ"], "89": [11713, "XHZ"], "90": [14522, "XHZ"], "91": [2438, "XHZ"], "92": [5247, "XHZ"], "93": [8056, "XHZ"], "94": [10865, "XHZ"], "95": [13674, "XHZ"], "96": [1590, "XHZ"], "97": [4399, "XHZ"], "98": [7208, "XHZ"], "99": [10017, "XHZ"], "100": [12826, "XHZ"], "101": [742, "XHZ"], "102": [3551, "XHZ"], "103": [6360, "XHZ"], "104": [9169, "XHZ"], "105": [11978, "XHZ"], "106": [14787, "XHZ"], "107": [2703, "XHZ"], "108": [5512, "XHZ"], "109": [8321, "XHZ"], "110": [11130, "XHZ"], "111": [13939, "XHZ"], "112": [1855, "XHZ"], "113": [4664, "XHZ"], "114": [7473, "XHZ"], "115": [10282, "XHZ"], "116": [13091, "XHZ"], "117": [1007, "XHZ"], "118": [3816, "XHZ"], "119": [6625, "XHZ"], "120": [9434, "XHZ"], "121": [12243, "XHZ"], "122": [159, "XHZ"], "123": [2968, "XHZ"], "124": [5777, "XHZ"], "125": [8586, "XHZ"], "126": [11395, "XHZ"], "127": [14204, "XHZ"], "128": [2120, "XHZ"], "129": [4929, "XHZ"], "130": [7738, "XHZ"], "131": [10547, "XHZ"], "132": [13356, "XHZ"], "133": [1272, "XHZ"], "134": [4081, "XHZ"], "135": [6890, "XHZ"], "136": [9699, "XHZ"], "137": [12508, "XHZ"], "138": [424, "XHZ"], "139": [3233, "XHZ"], "140": [6042, "XHZ"], "141": [8851, "XHZ"], "142": [11660, "XHZ"], "143": [14469, "XHZ"], "144": [2385, "XHZ"], "145": [5194, "XHZ"], "146": [8003, "XHZ"], "147": [10812, "XHZ"], "148": [13621, "XHZ"], "149": [1537, "XHZ"], "150": [4346, "XHZ"], "151": [7155, "XHZ"], "152": [9964, "XHZ"], "153": [12773, "XHZ"], "154": [689, "XHZ"], "155": [3498, "XHZ"], "156": [6307, "XHZ"], "157": [9116, "XHZ"], "158": [11925, "XHZ"], "159": [14734, "XHZ"], "160": [2650, "XHZ"], "161": [5459, "XHZ"], "162": [8268, "XHZ"], "163": [11077, "XHZ"], "164": [13886, "XHZ"], "165": [1802, "XHZ"], "166": [4611, "XHZ"], "167": [7420, "XHZ"], "168": [10229, "XHZ"], "169": [13038, "XHZ"], "170": [954, "XHZ"], "171": [3763, "XHZ"], "172": [6572, "XHZ"], "173": [9381, "XHZ"], "174": [12190, "XHZ"], "175": [106, "XHZ"], "176": [2915, "XHZ"], "177": [5724, "XHZ"], "178": [8533, "XHZ"], "179": [11342, "XHZ"], "180": [14151, "XHZ"], "181": [2067, "XHZ"], "182": [4876, "XHZ"], "183": [7685, "XHZ"], "184": [10494, "XHZ"], "185": [13303, "XHZ"], "186": [1219, "XHZ"], "187": [4028, "XHZ"], "188": [6837, "XHZ"], "189": [9646, "XHZ"], "190": [12455, "XHZ"], "191": [371, "XHZ"], "192": [3180, "XHZ"], "193": [5989, "XHZ"], "194": [8798, "XHZ"], "195": [11607, "XHZ"], "196": [14416, "XHZ"], "197": [2332, "XHZ"], "198": [5141, "XHZ"], "199": [7950, "XHZ"], "200": [10759, "XHZ"], "201": [13568, "XHZ"], "202": [1484, "XHZ"], "203": [4293, "XHZ"], "204": [7102, "XHZ"], "205": [9911, "XHZ"], "206": [12720, "XHZ"], "207": [636, "XHZ"], "208": [3445, "XHZ"], "209": [6254, "XHZ"], "210": [9063, "XHZ"], "211": [11872, "XHZ"], "212": [14681, "XHZ"], "213": [2597, "XHZ"], "214": [5406, "XHZ"], "215": [8215, "XHZ"], "216": [11024, "XHZ"], "217": [13833, "XHZ"], "218": [1749, "XHZ"], "219": [4558, "XHZ"], "220": [7367, "XHZ"], "221": [10176, "XHZ"], "222": [12985, "XHZ"], "223": [901, "XHZ"], "224": [3710, "XHZ"], "225": [6519, "XHZ"], "226": [9328, "XHZ"], "227": [12137, "XHZ"], "228": [53, "XHZ"], "229": [2862, "XHZ"], "230": [5671, "XHZ"], "231": [8480, "XHZ"], "232": [11289, "XHZ"], "233": [14098, "XHZ"], "234": [2014, "XHZ"], "235": [4823, "XHZ"], "236": [7632, "XHZ"], "237": [10441, "XHZ"], "238": [13250, "XHZ"], "239": [1166, "XHZ"], "240": [3975, "XHZ"], "241": [6784, "XHZ"], "242": [9593, "XHZ"], "243": [12402, "XHZ"], "244": [318, "XHZ"], "245": [3127, "XHZ"], "246": [5936, "XHZ"], "247": [8745, "XHZ"], "248": [11554, "XHZ"], "249": [14363, "XHZ"], "250": [2279, "XHZ"], "251": [5088, "XHZ"], "252": [7897, "XHZ"], "253": [10706, "XHZ"], "254": [13515, "XHZ"], "255": [1431, "XHZ"], "256": [4240, "XHZ"], "257": [7049, "XHZ"], "258": [9858, "XHZ"], "259": [12667, "XHZ"], "260": [583, "XHZ"], "261": [3392, "XHZ"], "262": [6201, "XHZ"], "263": [9010, "XHZ"], "264": [11819, "XHZ"], "265": [14628, "XHZ"], "266": [2544, "XHZ"], "267": [5353, "XHZ"], "268": [8162, "XHZ"], "269": [10971, "XHZ"], "270": [13780, "XHZ"], "271": [1696, "XHZ"], "272": [4505, "XHZ"], "273": [7314, "XHZ"], "274": [10123, "XHZ"], "275": [12932, "XHZ"], "276": [848, "XHZ"], "277": [3657, "XHZ"], "278": [6466, "XHZ"], "279": [9275, "XHZ"], "280": [12084, "XHZ"]}, "FHZ": {"0": [14893, "XHZ"], "1": [2809, "XHZ"], "2": [5618, "XHZ"], "3": [8427, "XHZ"], "4": [11236, "XHZ"], "5": [14045, "XHZ"], "6": [1961, "XHZ"], "7": [4770, "XHZ"], "8": [7579, "XHZ"], "9": [10388, "XHZ"], "10": [13197, "XHZ"], "11": [1113, "XHZ"], "12": [3922, "XHZ"], "13": [6731, "XHZ"], "14": [9540, "XHZ"], "15": [12349, "XHZ"], "16": [265, "XHZ"], "17": [3074, "XHZ"], "18": [5883, "XHZ"], "19": [8692, "XHZ"], "20": [11501, "XHZ"], "21": [14310, "XHZ"], "22": [2226, "XHZ"], "23": [5035, "XHZ"], "24": [7844, "XHZ"], "25": [10653, "XHZ"], "26": [13462, "XHZ"], "27": [1378, "XHZ"], "28": [4187, "XHZ"], "29": [6996, "XHZ"], "30": [9805, "XHZ"], "31": [12614, "XHZ"], "32": [530, "XHZ"], "33": [3339, "XHZ"], "34": [6148, "XHZ"], "35": [8957, "XHZ"], "36": [11766, "XHZ"], "37": [14575, "XHZ"], "38": [2491, "XHZ"], "39": [5300, "XHZ"], "40": [8109, "XHZ"], "41": [10918, "XHZ"], "42": [13727, "XHZ"], "43": [1643, "XHZ"], "44": [4452, "XHZ"], "45": [7261, "XHZ"], "46": [10070, "XHZ"], "47": [12879, "XHZ"], "48": [795, "XHZ"], "49": [3604, "XHZ"], "50": [6413, "XHZ"], "51": [9222, "XHZ"], "52": [12031, "XHZ"], "53": [14840, "XHZ"], "54": [2756, "XHZ"], "55": [5565, "XHZ"], "56": [8374, "XHZ"], "57": [11183, "XHZ"], "58": [13992, "XHZ"], "59": [1908, "XHZ"], "60": [4717, "XHZ"], "61": [7526, "XHZ"], "62": [10335, "XHZ"], "63": [13144, "XHZ"], "64": [1060, "XHZ"], "65": [3869, "XHZ"], "66": [6678, "XHZ"], "67": [9487, "XHZ"], "68": [12296, "XHZ"], "69": [212, "XHZ"], "70": [3021, "XHZ"], "71": [5830, "XHZ"], "72": [8639, "XHZ"], "73": [11448, "XHZ"], "74": [14257, "XHZ"], "75": [2173, "XHZ"], "76": [4982, "XHZ"], "77": [7791, "XHZ"], "78": [10600, "XHZ"], "79": [13409, "XHZ"], "80": [1325, "XHZ"], "81": [4134, "XHZ"], "82": [6943, "XHZ"], "83": [9752, "XHZ"], "84": [12561, "XHZ"], "85": [477, "XHZ"], "86": [3286, "XHZ"], "87": [6095, "XHZ"], "88": [8904, "XHZ"], "89": [11713, "XHZ"], "90": [14522, "XHZ"], "91": [2438, "XHZ"], "92": [5247, "XHZ"], "93": [8056, "XHZ"], "94": [10865, "XHZ"], "95": [13674, "XHZ"], "96": [1590, "XHZ"], "97": [4399, "XHZ"], "98": [7208, "XHZ"], "99": [10017, "XHZ"], "100": [12826, "XHZ"], "101": [742, "XHZ"], "102": [3551, "XHZ"], "103": [6360, "XHZ"], "104": [9169, "XHZ"], "105": [11978, "XHZ"], "106": [14787, "XHZ"], "107": [2703, "XHZ"], "108": [5512, "XHZ"], "109": [8321, "XHZ"], "110": [11130, "XHZ"], "111": [13939, "XHZ"], "112": [1855, "XHZ"], "113": [4664, "XHZ"], "114": [7473, "XHZ"], "115": [10282, "XHZ"], "116": [13091, "XHZ"], "117": [1007, "XHZ"], "118": [3816, "XHZ"], "119": [6625, "XHZ"], "120": [9434, "XHZ"], "121": [12243, "XHZ"], "122": [159, "XHZ"], "123": [2968, "XHZ"], "124": [5777, "XHZ"], "125": [8586, "XHZ"], "126": [11395, "XHZ"], "127": [14204, "XHZ"], "128": [2120, "XHZ"], "129": [4929, "XHZ"], "130": [7738, "XHZ"], "131": [10547, "XHZ"], "132": [13356, "XHZ"], "133": [1272, "XHZ"], "134": [4081, "XHZ"], "135": [6890, "XHZ"], "136": [9699, "XHZ"], "137": [12508, "XHZ"], "138": [424, "XHZ"], "139": [3233, "XHZ"], "140": [6042, "XHZ"], "141": [8851, "XHZ"], "142": [11660, "XHZ"], "143": [14469, "XHZ"], "144": [2385, "XHZ"], "145": [5194, "XHZ"], "146": [8003, "XHZ"], "147": [10812, "XHZ"], "148": [13621, "XHZ"], "149": [1537, "XHZ"], "150": [4346, "XHZ"], "151": [7155, "XHZ"], "152": [9964, "XHZ"], "153": [12773, "XHZ"], "154": [689, "XHZ"], "155": [3498, "XHZ"], "156": [6307, "XHZ"], "157": [9116, "XHZ"], "158": [11925, "XHZ"], "159": [14734, "XHZ"], "160": [2650, "XHZ"], "161": [5459, "XHZ"], "162": [8268, "XHZ"], "163": [11077, "XHZ"], "164": [13886, "XHZ"], "165": [1802, "XHZ"], "166": [4611, "XHZ"], "167": [7420, "XHZ"], "168": [10229, "XHZ"], "169": [13038, "XHZ"], "170": [954, "XHZ"], "171": [3763, "XHZ"], "172": [6572, "XHZ"], "173": [9381, "XHZ"], "174": [12190, "XHZ"], "175": [106, "XHZ"], "176": [2915, "XHZ"], "177": [5724, "XHZ"], "178": [8533, "XHZ"], "179": [11342, "XHZ"], "180": [14151, "XHZ"], "181": [2067, "XHZ"], "182": [4876, "XHZ"], "183": [7685, "XHZ"], "184": [10494, "XHZ"], "185": [13303, "XHZ"], "186": [1219, "XHZ"], "187": [4028, "XHZ"], "188": [6837, "XHZ"], "189": [9646, "XHZ"], "190": [12455, "XHZ"], "191": [371, "XHZ"], "192": [3180, "XHZ"], "193": [5989, "XHZ"], "194": [8798, "XHZ"], "195": [11607, "XHZ"], "196": [14416, "XHZ"], "197": [2332, "XHZ"], "198": [5141, "XHZ"], "199": [7950, "XHZ"], "200": [10759, "XHZ"], "201": [13568, "XHZ"], "202": [1484, "XHZ"], "203": [4293, "XHZ"], "204": [7102, "XHZ"], "205": [9911, "XHZ"], "206": [12720, "XHZ"], "207": [636, "XHZ"], "208": [3445, "XHZ"], "209": [6254, "XHZ"], "210": [9063, "XHZ"], "211": [11872, "XHZ"], "212": [14681, "XHZ"], "213": [2597, "XHZ"], "214": [5406, "XHZ"], "215": [8215, "XHZ"], "216": [11024, "XHZ"], "217": [13833, "XHZ"], "218": [1749, "XHZ"], "219": [4558, "XHZ"], "220": [7367, "XHZ"], "221": [10176, "XHZ"], "222": [12985, "XHZ"], "223": [901, "XHZ"], "224": [3710, "XHZ"], "225": [6519, "XHZ"], "226": [9328, "XHZ"], "227": [12137, "XHZ"], "228": [53, "XHZ"], "229": [2862, "XHZ"], "230": [5671, "XHZ"], "231": [8480, "XHZ"], "232": [11289, "XHZ"], "233": [14098, "XHZ"], "234": [2014, "XHZ"], "235": [4823, "XHZ"], "236": [7632, "XHZ"], "237": [10441, "XHZ"], "238": [13250, "XHZ"], "239": [1166, "XHZ"], "240": [3975, "XHZ"], "241": [6784, "XHZ"], "242": [9593, "XHZ"], "243": [12402, "XHZ"], "244": [318, "XHZ"], "245": [3127, "XHZ"], "246": [5936, "XHZ"], "247": [8745, "XHZ"], "248": [11554, "XHZ"], "249": [14363, "XHZ"], "250": [2279, "XHZ"], "251": [5088, "XHZ"], "252": [7897, "XHZ"], "253": [10706, "XHZ"], "254": [13515, "XHZ"], "255": [1431, "XHZ"], "256": [4240, "XHZ"], "257": [7049, "XHZ"], "258": [9858, "XHZ"], "259": [12667, "XHZ"], "260": [583, "XHZ"], "261": [3392, "XHZ"], "262": [6201, "XHZ"], "263": [9010, "XHZ"], "264": [11819, "XHZ"], "265": [14628, "XHZ"], "266": [2544, "XHZ"], "267": [5353, "XHZ"], "268": [8162, "XHZ"], "269": [10971, "XHZ"], "270": [13780, "XHZ"], "271": [1696, "XHZ"], "272": [4505, "XHZ"], "273": [7314, "XHZ"], "274": [10123, "XHZ"], "275": [12932, "XHZ"], "276": [848, "XHZ"], "277": [3657, "XHZ"], "278": [6466, "XHZ"], "279": [9275, "XHZ"], "280": [12084, "XHZ"]}, "RQZ": {"0": [14893, "XHZ"], "1": [2809, "XHZ"], "2": [5618, "XHZ"], "3": [8427, "XHZ"], "4": [11236, "XHZ"], "5": [14045, "XHZ"], "6": [1961, "XHZ"], "7": [4770, "XHZ"], "8": [7579, "XHZ"], "9": [10388, "XHZ"], "10": [13197, "XHZ"], "11": [1113, "XHZ"], "12": [3922, "XHZ"], "13": [6731, "XHZ"], "14": [9540, "XHZ"], "15": [12349, "XHZ"], "16": [265, "XHZ"], "17": [3074, "XHZ"], "18": [5883, "XHZ"], "19": [8692, "XHZ"], "20": [11501, "XHZ"], "21": [14310, "XHZ"], "22": [2226, "XHZ"], "23": [5035, "XHZ"], "24": [7844, "XHZ"], "25": [10653, "XHZ"], "26": [13462, "XHZ"], "27": [1378, "XHZ"], "28": [4187, "XHZ"], "29": [6996, "XHZ"], "30": [9805, "XHZ"], "31": [12614, "XHZ"], "32": [530, "XHZ"], "33": [3339, "XHZ"], "34": [6148, "XHZ"], "35": [8957, "XHZ"], "36": [11766, "XHZ"], "37": [14575, "XHZ"], "38": [2491, "XHZ"], "39": [5300, "XHZ"], "40": [8109, "XHZ"], "41": [10918, "XHZ"], "42": [13727, "XHZ"], "43": [1643, "XHZ"], "44": [4452, "XHZ"], "45": [7261, "XHZ"], "46": [10070, "XHZ"], "47": [12879, "XHZ"], "48": [795, "XHZ"], "49": [3604, "XHZ"], "50": [6413, "XHZ"], "51": [9222, "XHZ"], "52": [12031, "XHZ"], "53": [14840, "XHZ"], "54": [2756, "XHZ"], "55": [5565, "XHZ"], "56": [8374, "XHZ"], "57": [11183, "XHZ"], "58": [13992, "XHZ"], "59": [1908, "XHZ"], "60": [4717, "XHZ"], "61": [7526, "XHZ"], "62": [10335, "XHZ"], "63": [13144, "XHZ"], "64": [1060, "XHZ"], "65": [3869, "XHZ"], "66": [6678, "XHZ"], "67": [9487, "XHZ"], "68": [12296, "XHZ"], "69": [212, "XHZ"], "70": [3021, "XHZ"], "71": [5830, "XHZ"], "72": [8639, "XHZ"], "73": [11448, "XHZ"], "74": [14257, "XHZ"], "75": [2173, "XHZ"], "76": [4982, "XHZ"], "77": [7791, "XHZ"], "78": [10600, "XHZ"], "79": [13409, "XHZ"], "80": [1325, "XHZ"], "81": [4134, "XHZ"], "82": [6943, "XHZ"], "83": [9752, "XHZ"], "84": [12561, "XHZ"], "85": [477, "XHZ"], "86": [3286, "XHZ"], "87": [6095, "XHZ"], "88": [8904, "XHZ"], "89": [11713, "XHZ"], "90": [14522, "XHZ"], "91": [2438, "XHZ"], "92": [5247, "XHZ"], "93": [8056, "XHZ"], "94": [10865, "XHZ"], "95": [13674, "XHZ"], "96": [1590, "XHZ"], "97": [4399, "XHZ"], "98": [7208, "XHZ"], "99": [10017, "XHZ"], "100": [12826, "XHZ"], "101": [742, "XHZ"], "102": [3551, "XHZ"], "103": [6360, "XHZ"], "104": [9169, "XHZ"], "105": [11978, "XHZ"], "106": [14787, "XHZ"], "107": [2703, "XHZ"], "108": [5512, "XHZ"], "109": [8321, "XHZ"], "110": [11130, "XHZ"], "111": [13939, "XHZ"], "112": [1855, "XHZ"], "113": [4664, "XHZ"], "114": [7473, "XHZ"], "115": [10282, "XHZ"], "116": [13091, "XHZ"], "117": [1007, "XHZ"], "118": [3816, "XHZ"], "119": [6625, "XHZ"], "120": [9434, "XHZ"], "121": [12243, "XHZ"], "122": [159, "XHZ"], "123": [2968, "XHZ"], "124": [5777, "XHZ"], "125": [8586, "XHZ"], "126": [11395, "XHZ"], "127": [14204, "XHZ"], "128": [2120, "XHZ"], "129": [4929, "XHZ"], "130": [7738, "XHZ"], "131": [10547, "XHZ"], "132": [13356, "XHZ"], "133": [1272, "XHZ"], "134": [4081, "XHZ"], "135": [6890, "XHZ"], "136": [9699, "XHZ"], "137": [12508, "XHZ"], "138": [424, "XHZ"], "139": [3233, "XHZ"], "140": [6042, "XHZ"], "141": [8851, "XHZ"], "142": [11660, "XHZ"], "143": [14469, "XHZ"], "144": [2385, "XHZ"], "145": [5194, "XHZ"], "146": [8003, "XHZ"], "147": [10812, "XHZ"], "148": [13621, "XHZ"], "149": [1537, "XHZ"], "150": [4346, "XHZ"], "151": [7155, "XHZ"], "152": [9964, "XHZ"], "153": [12773, "XHZ"], "154": [689, "XHZ"], "155": [3498, "XHZ"], "156": [6307, "XHZ"], "157": [9116, "XHZ"], "158": [11925, "XHZ"], "159": [14734, "XHZ"], "160": [2650, "XHZ"], "161": [5459, "XHZ"], "162": [8268, "XHZ"], "163": [11077, "XHZ"], "164": [13886, "XHZ"], "165": [1802, "XHZ"], "166": [4611, "XHZ"], "167": [7420, "XHZ"], "168": [10229, "XHZ"], "169": [13038, "XHZ"], "170": [954, "XHZ"], "171": [3763, "XHZ"], "172": [6572, "XHZ"], "173": [9381, "XHZ"], "174": [12190, "XHZ"], "175": [106, "XHZ"], "176": [2915, "XHZ"], "177": [5724, "XHZ"], "178": [8533, "XHZ"], "179": [11342, "XHZ"], "180": [14151, "XHZ"], "181": [2067, "XHZ"], "182": [4876, "XHZ"], "183": [7685, "XHZ"], "184": [10494, "XHZ"], "185": [13303, "XHZ"], "186": [1219, "XHZ"], "187": [4028, "XHZ"], "188": [6837, "XHZ"], "189": [9646, "XHZ"], "190": [12455, "XHZ"], "191": [371, "XHZ"], "192": [3180, "XHZ"], "193": [5989, "XHZ"], "194": [8798, "XHZ"], "195": [11607, "XHZ"], "196": [14416, "XHZ"], "197": [2332, "XHZ"], "198": [5141, "XHZ"], "199": [7950, "XHZ"], "200": [10759, "XHZ"], "201": [13568, "XHZ"], "202": [1484, "XHZ"], "203": [4293, "XHZ"], "204": [7102, "XHZ"], "205": [9911, "XHZ"], "206": [12720, "XHZ"], "207": [636, "XHZ"], "208": [3445, "XHZ"], "209": [6254, "XHZ"], "210": [9063, "XHZ"], "211": [11872, "XHZ"], "212": [14681, "XHZ"], "213": [2597, "XHZ"], "214": [5406, "XHZ"], "215": [8215, "XHZ"], "216": [11024, "XHZ"], "217": [13833, "XHZ"], "218": [1749, "XHZ"], "219": [4558, "XHZ"], "220": [7367, "XHZ"], "221": [10176, "XHZ"], "222": [12985, "XHZ"], "223": [901, "XHZ"], "224": [3710, "XHZ"], "225": [6519, "XHZ"], "226": [9328, "XHZ"], "227": [12137, "XHZ"], "228": [53, "XHZ"], "229": [2862, "XHZ"], "230": [5671, "XHZ"], "231": [8480, "XHZ"], "232": [11289, "XHZ"], "233": [14098, "XHZ"], "234": [2014, "XHZ"], "235": [4823, "XHZ"], "236": [7632, "XHZ"], "237": [10441, "XHZ"], "238": [13250, "XHZ"], "239": [1166, "XHZ"], "240": [3975, "XHZ"], "241": [6784, "XHZ"], "242": [9593, "XHZ"], "243": [12402, "XHZ"], "244": [318, "XHZ"], "245": [3127, "XHZ"], "246": [5936, "XHZ"], "247": [8745, "XHZ"], "248": [11554, "XHZ"], "249": [14363, "XHZ"], "250": [2279, "XHZ"], "251": [5088, "XHZ"], "252": [7897, "XHZ"], "253": [10706, "XHZ"], "254": [13515, "XHZ"], "255": [1431, "XHZ"], "256": [4240, "XHZ"], "257": [7049, "XHZ"], "258": [9858, "XHZ"], "259": [12667, "XHZ"], "260": [583, "XHZ"], "261": [3392, "XHZ"], "262": [6201, "XHZ"], "263": [9010, "XHZ"], "264": [11819, "XHZ"], "265": [14628, "XHZ"], "266": [2544, "XHZ"], "267": [5353, "XHZ"], "268": [8162, "XHZ"], "269": [10971, "XHZ"], "270": [13780, "XHZ"], "271": [1696, "XHZ"], "272": [4505, "XHZ"], "273": [7314, "XHZ"], "274": [10123, "XHZ"], "275": [12932, "XHZ"], "276": [848, "XHZ"], "277": [3657, "XHZ"], "278": [6466, "XHZ"], "279": [9275, "XHZ"], "280": [12084, "XHZ"]}, "LXZ": {"0": [14893, "XHZ"], "1": [2809, "XHZ"], "2": [5618, "XHZ"], "3": [8427, "XHZ"], "4": [11236, "XHZ"], "5": [14045, "XHZ"], "6": [1961, "XHZ"], "7": [4770, "XHZ"], "8": [7579, "XHZ"], "9": [10388, "XHZ"], "10": [13197, "XHZ"], "11": [1113, "XHZ"], "12": [3922, "XHZ"], "13": [6731, "XHZ"], "14": [9540, "XHZ"], "15": [12349, "XHZ"], "16": [265, "XHZ"], "17": [3074, "XHZ"], "18": [5883, "XHZ"], "19": [8692, "XHZ"], "20": [11501, "XHZ"], "21": [14310, "XHZ"], "22": [2226, "XHZ"], "23": [5035, "XHZ"], "24": [7844, "XHZ"], "25": [10653, "XHZ"], "26": [13462, "XHZ"], "27": [1378, "XHZ"], "28": [4187, "XHZ"], "29": [6996, "XHZ"], "30": [9805, "XHZ"], "31": [12614, "XHZ"], "32": [530, "XHZ"], "33": [3339, "XHZ"], "34": [6148, "XHZ"], "35": [8957, "XHZ"], "36": [11766, "XHZ"], "37": [14575, "XHZ"], "38": [2491, "XHZ"], "39": [5300, "XHZ"], "40": [8109, "XHZ"], "41": [10918, "XHZ"], "42": [13727, "XHZ"], "43": [1643, "XHZ"], "44": [4452, "XHZ"], "45": [7261, "XHZ"], "46": [10070, "XHZ"], "47": [12879, "XHZ"], "48": [795, "XHZ"], "49": [3604, "XHZ"], "50": [6413, "XHZ"], "51": [9222, "XHZ"], "52": [12031, "XHZ"], "53": [14840, "XHZ"], "54": [2756, "XHZ"], "55": [5565, "XHZ"], "56": [8374, "XHZ"], "57": [11183, "XHZ"], "58": [13992, "XHZ"], "59": [1908, "XHZ"], "60": [4717, "XHZ"], "61": [7526, "XHZ"], "62": [10335, "XHZ"], "63": [13144, "XHZ"], "64": [1060, "XHZ"], "65": [3869, "XHZ"], "66": [6678, "XHZ"], "67": [9487, "XHZ"], "68": [12296, "XHZ"], "69": [212, "XHZ"], "70": [3021, "XHZ"], "71": [5830, "XHZ"], "72": [8639, "XHZ"], "73": [11448, "XHZ"], "74": [14257, "XHZ"], "75": [2173, "XHZ"], "76": [4982, "XHZ"], "77": [7791, "XHZ"], "78": [10600, "XHZ"], "79": [13409, "XHZ"], "80": [1325, "XHZ"], "81": [4134, "XHZ"], "82": [6943, "XHZ"], "83": [9752, "XHZ"], "84": [12561, "XHZ"], "85": [477, "XHZ"], "86": [3286, "XHZ"], "87": [6095, "XHZ"], "88": [8904, "XHZ"], "89": [11713, "XHZ"], "90": [14522, "XHZ"], "91": [2438, "XHZ"], "92": [5247, "XHZ"], "93": [8056, "XHZ"], "94": [10865, "XHZ"], "95": [13674, "XHZ"], "96": [1590, "XHZ"], "97": [4399, "XHZ"], "98": [7208, "XHZ"], "99": [10017, "XHZ"], "100": [12826, "XHZ"], "101": [742, "XHZ"], "102": [3551, "XHZ"], "103": [6360, "XHZ"], "104": [9169, "XHZ"], "105": [11978, "XHZ"], "106": [14787, "XHZ"], "107": [2703, "XHZ"], "108": [5512, "XHZ"], "109": [8321, "XHZ"], "110": [11130, "XHZ"], "111": [13939, "XHZ"], "112": [1855, "XHZ"], "113": [4664, "XHZ"], "114": [7473, "XHZ"], "115": [10282, "XHZ"], "116": [13091, "XHZ"], "117": [1007, "XHZ"], "118": [3816, "XHZ"], "119": [6625, "XHZ"], "120": [9434, "XHZ"], "121": [12243, "XHZ"], "122": [159, "XHZ"], "123": [2968, "XHZ"], "124": [5777, "XHZ"], "125": [8586, "XHZ"], "126": [11395, "XHZ"], "127": [14204, "XHZ"], "128": [2120, "XHZ"], "129": [4929, "XHZ"], "130": [7738, "XHZ"], "131": [10547, "XHZ"], "132": [13356, "XHZ"], "133": [1272, "XHZ"], "134": [4081, "XHZ"], "135": [6890, "XHZ"], "136": [9699, "XHZ"], "137": [12508, "XHZ"], "138": [424, "XHZ"], "139": [3233, "XHZ"], "140": [6042, "XHZ"], "141": [8851, "XHZ"], "142": [11660, "XHZ"], "143": [14469, "XHZ"], "144": [2385, "XHZ"], "145": [5194, "XHZ"], "146": [8003, "XHZ"], "147": [10812, "XHZ"], "148": [13621, "XHZ"], "149": [1537, "XHZ"], "150": [4346, "XHZ"], "151": [7155, "XHZ"], "152": [9964, "XHZ"], "153": [12773, "XHZ"], "154": [689, "XHZ"], "155": [3498, "XHZ"], "156": [6307, "XHZ"], "157": [9116, "XHZ"], "158": [11925, "XHZ"], "159": [14734, "XHZ"], "160": [2650, "XHZ"], "161": [5459, "XHZ"], "162": [8268, "XHZ"], "163": [11077, "XHZ"], "164": [13886, "XHZ"], "165": [1802, "XHZ"], "166": [4611, "XHZ"], "167": [7420, "XHZ"], "168": [10229, "XHZ"], "169": [13038, "XHZ"], "170": [954, "XHZ"], "171": [3763, "XHZ"], "172": [6572, "XHZ"], "173": [9381, "XHZ"], "174": [12190, "XHZ"], "175": [106, "XHZ"], "176": [2915, "XHZ"], "177": [5724, "XHZ"], "178": [8533, "XHZ"], "179": [11342, "XHZ"], "180": [14151, "XHZ"], "181": [2067, "XHZ"], "182": [4876, "XHZ"], "183": [7685, "XHZ"], "184": [10494, "XHZ"], "185": [13303, "XHZ"], "186": [1219, "XHZ"], "187": [4028, "XHZ"], "188": [6837, "XHZ"], "189": [9646, "XHZ"], "190": [12455, "XHZ"], "191": [371, "XHZ"], "192": [3180, "XHZ"], "193": [5989, "XHZ"], "194": [8798, "XHZ"], "195": [11607, "XHZ"], "196": [14416, "XHZ"], "197": [2332, "XHZ"], "198": [5141, "XHZ"], "199": [7950, "XHZ"], "200": [10759, "XHZ"], "201": [13568, "XHZ"], "202": [1484, "XHZ"], "203": [4293, "XHZ"], "204": [7102, "XHZ"], "205": [9911, "XHZ"], "206": [12720, "XHZ"], "207": [636, "XHZ"], "208": [3445, "XHZ"], "209": [6254, "XHZ"], "210": [9063, "XHZ"], "211": [11872, "XHZ"], "212": [14681, "XHZ"], "213": [2597, "XHZ"], "214": [5406, "XHZ"], "215": [8215, "XHZ"], "216": [11024, "XHZ"], "217": [13833, "XHZ"], "218": [1749, "XHZ"], "219": [4558, "XHZ"], "220": [7367, "XHZ"], "221": [10176, "XHZ"], "222": [12985, "XHZ"], "223": [901, "XHZ"], "224": [3710, "XHZ"], "225": [6519, "XHZ"], "226": [9328, "XHZ"], "227": [12137, "XHZ"], "228": [53, "XHZ"], "229": [2862, "XHZ"], "230": [5671, "XHZ"], "231": [8480, "XHZ"], "232": [11289, "XHZ"], "233": [14098, "XHZ"], "234": [2014, "XHZ"], "235": [4823, "XHZ"], "236": [7632, "XHZ"], "237": [10441, "XHZ"], "238": [13250, "XHZ"], "239": [1166, "XHZ"], "240": [3975, "XHZ"], "241": [6784, "XHZ"], "242": [9593, "XHZ"], "243": [12402, "XHZ"], "244": [318, "XHZ"], "245": [3127, "XHZ"], "246": [5936, "XHZ"], "247": [8745, "XHZ"], "248": [11554, "XHZ"], "249": [14363, "XHZ"], "250": [2279, "XHZ"], "251": [5088, "XHZ"], "252": [7897, "XHZ"], "253": [10706, "XHZ"], "254": [13515, "XHZ"], "255": [1431, "XHZ"], "256": [4240, "XHZ"], "257": [7049, "XHZ"], "258": [9858, "XHZ"], "259": [12667, "XHZ"], "260": [583, "XHZ"], "261": [3392, "XHZ"], "262": [6201, "XHZ"], "263": [9010, "XHZ"], "264": [11819, "XHZ"], "265": [14628, "XHZ"], "266": [2544, "XHZ"], "267": [5353, "XHZ"], "268": [8162, "XHZ"], "269": [10971, "XHZ"], "270": [13780, "XHZ"], "271": [1696, "XHZ"], "272": [4505, "XHZ"], "273": [7314, "XHZ"], "274": [10123, "XHZ"], "275": [12932, "XHZ"], "276": [848, "XHZ"], "277": [3657, "XHZ"], "278": [6466, "XHZ"], "279": [9275, "XHZ"], "280": [12084, "XHZ"]}}}